MANIFEST.in
README.txt
setup.cfg
setup.py
Products/__init__.py
Products.ifSearchMonitor.egg-info/PKG-INFO
Products.ifSearchMonitor.egg-info/SOURCES.txt
Products.ifSearchMonitor.egg-info/dependency_links.txt
Products.ifSearchMonitor.egg-info/entry_points.txt
Products.ifSearchMonitor.egg-info/namespace_packages.txt
Products.ifSearchMonitor.egg-info/not-zip-safe
Products.ifSearchMonitor.egg-info/paster_plugins.txt
Products.ifSearchMonitor.egg-info/requires.txt
Products.ifSearchMonitor.egg-info/top_level.txt
Products/ifSearchMonitor/INSTALL.txt
Products/ifSearchMonitor/LICENSE.GPL
Products/ifSearchMonitor/LICENSE.txt
Products/ifSearchMonitor/README.txt
Products/ifSearchMonitor/__init__.py
Products/ifSearchMonitor/config.py
Products/ifSearchMonitor/ifSearchMonitorTool.py
Products/ifSearchMonitor/refresh.txt
Products/ifSearchMonitor/tool.gif
Products/ifSearchMonitor/version.txt
Products/ifSearchMonitor/Extensions/__init__.py
Products/ifSearchMonitor/Extensions/install.py
Products/ifSearchMonitor/skins/ifSearchMonitor/browseContent.pt
Products/ifSearchMonitor/skins/ifSearchMonitor/ifSearchMonitor_recommend.cpt
Products/ifSearchMonitor/skins/ifSearchMonitor/ifSearchMonitor_recommend.cpt.metadata
Products/ifSearchMonitor/skins/ifSearchMonitor/ifSearchMonitor_recommended.pt
Products/ifSearchMonitor/skins/ifSearchMonitor/ifSearchMonitor_stats.pt
Products/ifSearchMonitor/skins/ifSearchMonitor/manage_recommend.cpy
Products/ifSearchMonitor/skins/ifSearchMonitor/manage_recommend.cpy.metadata
Products/ifSearchMonitor/skins/ifSearchMonitor/recommend.js
Products/ifSearchMonitor/skins/ifSearchMonitor/search.pt
Products/ifSearchMonitor/skins/ifSearchMonitor/searchContent.js
Products/ifSearchMonitor/skins/ifSearchMonitor/searchContent.pt
Products/ifSearchMonitor/skins/ifSearchMonitor/tool.gif
Products/ifSearchMonitor/tests/__init__.py
Products/ifSearchMonitor/tests/framework.py
Products/ifSearchMonitor/tests/testSuggest.py