Metadata-Version: 1.0
Name: Products.ifSearchMonitor
Version: 0.4dev
Summary: Compatible with Plone 3+
Home-page: http://svn.plone.org/svn/collective/
Author: sHINY
Author-email: shiny@mahiti.org
License: GPL
Keywords: zope plone ifSearchMonitor
Platform: UNKNOWN
Classifier: Framework :: Plone
Classifier: Programming Language :: Python
Classifier: Topic :: Software Development :: Libraries :: Python Modules
